pyosmapi/__init__.py
pyosmapi/exceptions.py
pyosmapi/osm_api.py
pyosmapi/osm_util.py
pyosmapi-0.0.1.dist-info/LICENSE
pyosmapi-0.0.1.dist-info/METADATA
pyosmapi-0.0.1.dist-info/WHEEL
pyosmapi-0.0.1.dist-info/top_level.txt
pyosmapi-0.0.1.dist-info/RECORD
