Metadata-Version: 2.1
Name: pyosmapi
Version: 0.0.1
Summary: Open Street Map API Wrapper in Python
Home-page: https://github.com/jonycoo/py-osmapi
Author: jonycoo
Author-email: jonathan.koehler.7@web.de
License: MIT
Keywords: osm,openstreetmap,wrapper,api
Platform: UNKNOWN
Classifier: Programming Language :: Python :: 3
Classifier: License :: OSI Approved :: MIT License
Classifier: Operating System :: OS Independent
Requires-Python: >=3.6
Requires-Dist: requests
